README.rst
setup.py
dev_postman.egg-info/PKG-INFO
dev_postman.egg-info/SOURCES.txt
dev_postman.egg-info/dependency_links.txt
dev_postman.egg-info/top_level.txt
postman/__init__.py
postman/admin.py
postman/api.py
postman/apps.py
postman/context_processors.py
postman/fields.py
postman/forms.py
postman/future_1_4.py
postman/future_1_5.py
postman/models.py
postman/module_for_tests.py
postman/query.py
postman/tests.py
postman/urls.py
postman/urls_for_tests.py
postman/utils.py
postman/views.py
postman/management/__init__.py
postman/management/commands/__init__.py
postman/management/commands/postman_checkup.py
postman/management/commands/postman_cleanup.py
postman/migrations/0001_initial.py
postman/migrations/0002_message_subject1.py
postman/migrations/0003_auto_20160510_1448.py
postman/migrations/0004_remove_message_subject1.py
postman/migrations/0005_message_avatar.py
postman/migrations/0006_remove_message_avatar.py
postman/migrations/0007_message_response.py
postman/migrations/0008_auto_20160602_1204.py
postman/migrations/0009_auto_20160602_1205.py
postman/migrations/0010_auto_20160602_1333.py
postman/migrations/0011_auto_20160602_1342.py
postman/migrations/0012_auto_20160609_0902.py
postman/migrations/0013_auto_20160609_0907.py
postman/migrations/0014_auto_20160609_0943.py
postman/migrations/0015_auto_20160609_0945.py
postman/migrations/0016_auto_20160609_1033.py
postman/migrations/0017_auto_20160609_1049.py
postman/migrations/0018_message_response1.py
postman/migrations/0019_remove_message_response1.py
postman/migrations/0020_remove_message_response.py
postman/migrations/0021_auto_20160622_1054.py
postman/migrations/0022_remove_message_user_profile.py
postman/migrations/__init__.py
postman/templatetags/__init__.py
postman/templatetags/pagination_tags.py
postman/templatetags/postman_admin_modify.py
postman/templatetags/postman_tags.py